[
  {
    "id": 1,
    "name": "Pyramids of Giza",
    "governorate": "Giza",
    "city": "Giza",
    "coordinates": {
      "lat": 29.9792,
      "lng": 31.1342
    },
    "description": "The last remaining Wonder of the Ancient World, the Pyramids of Giza are monumental tombs built for the Pharaohs Khufu, Khafre, and Menkaure.",
    "history": "Constructed during the Fourth Dynasty of the Old Kingdom around 2600–2500 BC, the pyramids served as royal tombs and were part of a vast funerary complex including temples and smaller pyramids.",
    "images": [
      "https://images.pexels.com/photos/240444/pexels-photo-240444.jpeg",
      "https://images.pexels.com/photos/169647/pexels-photo-169647.jpeg"
    ],
    "category": "Historical",
    "rating": 4.9,
    "visitorsPerYear": 14500000
  },
  {
    "id": 2,
    "name": "Karnak Temple",
    "governorate": "Luxor",
    "city": "Luxor",
    "coordinates": {
      "lat": 25.7188,
      "lng": 32.6573
    },
    "description": "One of the largest religious complexes in the world, dedicated primarily to the Theban triad of Amun, Mut, and Khonsu.",
    "history": "Karnak was developed over more than 1,500 years, from the Middle Kingdom to the Ptolemaic period, with each pharaoh adding chapels, pylons, obelisks, and statues.",
    "images": [
      "https://images.pexels.com/photos/1328552/pexels-photo-1328552.jpeg"
    ],
    "category": "Historical",
    "rating": 4.8,
    "visitorsPerYear": 5000000
  },
  {
    "id": 3,
    "name": "Luxor Temple",
    "governorate": "Luxor",
    "city": "Luxor",
    "coordinates": {
      "lat": 25.6995,
      "lng": 32.6396
    },
    "description": "A majestic temple complex on the east bank of the Nile, connected to Karnak via the Avenue of Sphinxes.",
    "history": "Built mainly by Amenhotep III and Ramesses II, Luxor Temple was dedicated to the rejuvenation of kingship and played a central role in the Opet Festival.",
    "images": [
      "https://images.pexels.com/photos/220888/pexels-photo-220888.jpeg"
    ],
    "category": "Historical",
    "rating": 4.7,
    "visitorsPerYear": 4200000
  },
  {
    "id": 4,
    "name": "Abu Simbel Temples",
    "governorate": "Aswan",
    "city": "Abu Simbel",
    "coordinates": {
      "lat": 22.3372,
      "lng": 31.6258
    },
    "description": "Twin rock-cut temples built by Ramesses II, famous for their colossal statues and sunlight alignment phenomena.",
    "history": "Carved in the 13th century BC, the temples were relocated in the 1960s to save them from the waters of Lake Nasser after the construction of the Aswan High Dam.",
    "images": [
      "https://images.pexels.com/photos/959508/pexels-photo-959508.jpeg"
    ],
    "category": "Historical",
    "rating": 4.9,
    "visitorsPerYear": 1500000
  },
  {
    "id": 5,
    "name": "The Egyptian Museum",
    "governorate": "Cairo",
    "city": "Cairo",
    "coordinates": {
      "lat": 30.0478,
      "lng": 31.2336
    },
    "description": "Historic museum on Tahrir Square housing one of the world's most important collections of ancient Egyptian antiquities.",
    "history": "Opened in 1902, the museum showcases treasures from the tomb of Tutankhamun, royal mummies, and thousands of artifacts spanning Egypt's long history.",
    "images": [
      "https://images.pexels.com/photos/209065/pexels-photo-209065.jpeg"
    ],
    "category": "Museum",
    "rating": 4.6,
    "visitorsPerYear": 3000000
  },
  {
    "id": 6,
    "name": "Citadel of Saladin",
    "governorate": "Cairo",
    "city": "Cairo",
    "coordinates": {
      "lat": 30.0299,
      "lng": 31.2617
    },
    "description": "Medieval Islamic fortification overlooking Cairo, home to the iconic Muhammad Ali Mosque.",
    "history": "Begun by Salah ad-Din (Saladin) in the 12th century to defend against Crusader attacks, the Citadel later became the seat of Egypt's rulers for centuries.",
    "images": [
      "https://images.pexels.com/photos/460680/pexels-photo-460680.jpeg"
    ],
    "category": "Historical",
    "rating": 4.5,
    "visitorsPerYear": 2200000
  },
  {
    "id": 7,
    "name": "Bibliotheca Alexandrina",
    "governorate": "Alexandria",
    "city": "Alexandria",
    "coordinates": {
      "lat": 31.2089,
      "lng": 29.9092
    },
    "description": "Modern cultural center and library commemorating the ancient Library of Alexandria, located on the Mediterranean coast.",
    "history": "Inaugurated in 2002, the complex includes a vast library, museums, galleries, and a planetarium, celebrating knowledge and cultural exchange.",
    "images": [
      "https://images.pexels.com/photos/460736/pexels-photo-460736.jpeg"
    ],
    "category": "Cultural",
    "rating": 4.7,
    "visitorsPerYear": 1800000
  },
  {
    "id": 8,
    "name": "Philae Temple",
    "governorate": "Aswan",
    "city": "Aswan",
    "coordinates": {
      "lat": 24.0240,
      "lng": 32.8840
    },
    "description": "Temple complex dedicated to the goddess Isis, beautifully situated on an island in the Nile near Aswan.",
    "history": "The temple was relocated to Agilkia Island in the 1960s as part of the UNESCO campaign to save Nubian monuments from flooding caused by the Aswan High Dam.",
    "images": [
      "https://images.pexels.com/photos/210307/pexels-photo-210307.jpeg"
    ],
    "category": "Historical",
    "rating": 4.6,
    "visitorsPerYear": 1600000
  },
  {
    "id": 9,
    "name": "Valley of the Kings",
    "governorate": "Luxor",
    "city": "Luxor (West Bank)",
    "coordinates": {
      "lat": 25.7402,
      "lng": 32.6014
    },
    "description": "Royal necropolis on the west bank of the Nile, containing tombs of New Kingdom pharaohs including Tutankhamun and Ramesses II.",
    "history": "Used as a burial ground for nearly 500 years, the valley contains more than 60 tombs richly decorated with scenes from ancient Egyptian religion.",
    "images": [
      "https://images.pexels.com/photos/71241/pexels-photo-71241.jpeg"
    ],
    "category": "Historical",
    "rating": 4.9,
    "visitorsPerYear": 2500000
  },
  {
    "id": 10,
    "name": "Sharm El Sheikh (Naama Bay)",
    "governorate": "South Sinai",
    "city": "Sharm El Sheikh",
    "coordinates": {
      "lat": 27.9158,
      "lng": 34.3299
    },
    "description": "Famous Red Sea resort area known for its beaches, coral reefs, and vibrant nightlife.",
    "history": "Developed in the late 20th century as a major tourism hub, Sharm El Sheikh attracts divers and holidaymakers from around the world.",
    "images": [
      "https://images.pexels.com/photos/248797/pexels-photo-248797.jpeg"
    ],
    "category": "Beach",
    "rating": 4.6,
    "visitorsPerYear": 6000000
  }
]

